llm_cloudflare.py
llm_cloudflare-0.5.6.dist-info/LICENSE
llm_cloudflare-0.5.6.dist-info/METADATA
llm_cloudflare-0.5.6.dist-info/WHEEL
llm_cloudflare-0.5.6.dist-info/entry_points.txt
llm_cloudflare-0.5.6.dist-info/top_level.txt
llm_cloudflare-0.5.6.dist-info/RECORD
