Metadata-Version: 2.2
Name: llm-cloudflare
Version: 0.5.6
Summary: An LLM CLI plugin for Cloudflare Workers AI models.
Author: elithrar
License: Apache-2.0
Project-URL: Homepage, https://github.com/elithrar/llm-cloudflare
Project-URL: Issues, https://github.com/elithrar/llm-cloudflare/issues
Project-URL: CI, https://github.com/elithrar/llm-cloudflare/actions
Project-URL: Changelog, https://github.com/elithrar/llm-cloudflare/releases
Classifier: License :: OSI Approved :: Apache Software License
License-File: LICENSE
Requires-Dist: llm
Requires-Dist: OpenAI
